{"_id":{"$oid":"593ff50016ff378afdf59639"},"name":"ADN Galeria","address":"c/ Enric Granados, 49","telf":"934 510 064","__v":0}
{"_id":{"$oid":"593ff50016ff378afdf5963b"},"name":"àngels barcelona-espai2","address":"c/ dels Àngels, 16","image":"http://angelsbarcelona.com/images/events/event_A39_web_4813.jpg","telf":"+34 93 412 54 00","openingTimes":"Mon - Fri: 10:30h - 19h. \nSaturdays and all other times, call for an appointment","__v":0}
{"_id":{"$oid":"593ff50016ff378afdf5963a"},"name":"Ana Mas Projects","address":"Isaac Peral, 7","image":"http://www.anamasprojects.com/wp-content/uploads/DSC_2548-900x601.jpg","url":"http://www.anamasprojects.com/en/","telf":"","__v":0}
{"_id":{"$oid":"593ff50016ff378afdf5963c"},"name":"Art Deal Project","address":"Llibertat, 44","telf":"93 269 63 22","__v":0}
{"_id":{"$oid":"593ff50016ff378afdf5963d"},"name":"Arts Santa Mònica","address":"La Rambla 7","telf":"933 162 810","__v":0}
{"_id":{"$oid":"593ff50016ff378afdf5963e"},"name":"Arxiu Fotogràfic de Barce…","address":"Plaça Pons i Clerch 2","telf":"932 563 420","__v":0}
{"_id":{"$oid":"593ff50016ff378afdf5963f"},"name":"Arxiu Històric Ciutat","address":"Sta. Llúcia 1","telf":"933 181 195","__v":0}
{"_id":{"$oid":"593ff50016ff378afdf59640"},"name":"B the travel brand Xperie…","address":"Avinguda Diagonal, 512","telf":"","__v":0}
{"_id":{"$oid":"593ff50016ff378afdf59641"},"name":"Background Gallery","address":"c/ Joaquín Costa 38","telf":"934 120 950","__v":0}
{"_id":{"$oid":"593ff50016ff378afdf59642"},"name":"Blueproject Foundation","address":"Princesa 57","telf":"931 824 371","__v":0}
{"_id":{"$oid":"593ff50016ff378afdf59643"},"name":"C d'Art Tecla Sala","address":"Av. Josep Tarradellas 44","telf":"933 385 771","__v":0}
{"_id":{"$oid":"593ff50016ff378afdf59644"},"name":"C. Cívic Can Basté","address":"Pg. Fabra i Puig 274-276","telf":"934 206 651","__v":0}
{"_id":{"$oid":"593ff50016ff378afdf59645"},"name":"C. Cívic Can Felipa","address":"Pallars 277","telf":"932 563 840","__v":0}
{"_id":{"$oid":"593ff50016ff378afdf59646"},"name":"C. Cívic Pati Llimona","address":"Regomir 3","image":"https://patillimona.net/wp-content/uploads/2013/11/Pati-Llimona-04-SG1619_0688.jpg","telf":"932566100","__v":0}
{"_id":{"$oid":"593ff50016ff378afdf59647"},"name":"CaixaForum","address":"Av. Francesc Ferrer i Guàrdia 6-8","telf":"934 768 600","__v":0}
{"_id":{"$oid":"593ff50016ff378afdf59648"},"name":"Can Framis - M. Pintura C…","address":"Roc Boronat 116-126","telf":"933 208 736","__v":0}
{"_id":{"$oid":"593ff50016ff378afdf59649"},"name":"Casa Elizalde","address":"València 302","telf":"934 880 590","__v":0}
{"_id":{"$oid":"593ff50016ff378afdf5964a"},"name":"Castell de Montjuïc","address":"Carretera de Montjuïc 66","telf":"","__v":0}
{"_id":{"$oid":"593ff50016ff378afdf5964b"},"name":"CCCB","address":"Montalegre 5","telf":"933 064 100","__v":0}
{"_id":{"$oid":"593ff50016ff378afdf5964c"},"name":"CEM Frontó Colom","address":"Rambla Santa Mònica 18","telf":"","__v":0}
{"_id":{"$oid":"593ff50016ff378afdf5964d"},"name":"Centre Cívic Golferichs","address":"Gran Via 491","telf":"933 237 790","__v":0}
{"_id":{"$oid":"593ff50016ff378afdf5964e"},"name":"Círculo del Arte","address":"Princesa 52","telf":"932 688 800","__v":0}
{"_id":{"$oid":"593ff50016ff378afdf5964f"},"name":"CosmoCaixa","address":"Teodor Roviralta 47-51","image":"http://cdn02.visitbarcelona.com/files/5531-4090-imagenCAT/BarcelonaCosmoCaixa-T24-a_O.jpg","telf":"932 126 050","__v":0}
{"_id":{"$oid":"593ff50016ff378afdf59650"},"name":"Disseny Hub BCN","address":"Plaça de les Glòries Catalanes, 37-38","telf":"","__v":0}
{"_id":{"$oid":"593ff50016ff378afdf59651"},"name":"El Born CCM","address":"Plaça Comercial 12","telf":"","__v":0}
{"_id":{"$oid":"593ff50016ff378afdf59652"},"name":"El Diluvio Universal","address":"Guilleries, 2","telf":"","__v":0}
{"_id":{"$oid":"593ff50016ff378afdf59653"},"name":"El quadern robat","address":"Còrsega 267. Principal 2 B","telf":"93 368 36 72","__v":0}
{"_id":{"$oid":"593ff50016ff378afdf59654"},"name":"Espai 88","address":"Pamplona 88","telf":"","__v":0}
{"_id":{"$oid":"593ff50016ff378afdf59655"},"name":"Espai F. Català-Roca","address":"Llançà 21","telf":"933 237 790","__v":0}
{"_id":{"$oid":"593ff50016ff378afdf59656"},"name":"Espai Volart","address":"Ausiàs Marc 22","telf":"934817985","__v":0}
{"_id":{"$oid":"593ff50016ff378afdf59657"},"name":"Espronceda. Art \u0026a…","address":"Espronceda, 326","telf":"","__v":0}
{"_id":{"$oid":"593ff50016ff378afdf59658"},"name":"Fabra i Coats","address":"Sant Adrià 18-24","telf":"","__v":0}
{"_id":{"$oid":"593ff50016ff378afdf59659"},"name":"Fàbrica Trinxet","address":"Santa Eulàlia, 212","telf":"","__v":0}
{"_id":{"$oid":"593ff50016ff378afdf5965a"},"name":"Filmoteca de Catalunya","address":"Pl. Salvador Seguí 1-9","telf":"","__v":0}
{"_id":{"$oid":"593ff50016ff378afdf5965b"},"name":"Fundació Antoni Tàpies","address":"Aragó 255","telf":"934 870 315","__v":0}
{"_id":{"$oid":"593ff50016ff378afdf5965c"},"name":"Fundació Arranz-Bravo","address":"Av. Josep Tarradellas 44","telf":"","__v":0}
{"_id":{"$oid":"593ff50016ff378afdf5965d"},"name":"Fundació Foto Colectania","address":"Passeig Picasso, 14","telf":"932 171 626","__v":0}
{"_id":{"$oid":"593ff50016ff378afdf5965e"},"name":"Fundació Gaspar","address":"c/ Montcada, 25","telf":"","__v":0}
{"_id":{"$oid":"593ff50016ff378afdf5965f"},"name":"Fundació Joan Miró","address":"Parc de Montjuïc","telf":"934 439 470","__v":0}
{"_id":{"$oid":"593ff50016ff378afdf59660"},"name":"Fundació Setba","address":"Pl. Reial 10","telf":"934 813 696","__v":0}
{"_id":{"$oid":"593ff50016ff378afdf59661"},"name":"Fundació Suñol","address":"Pg. de Gràcia 98","telf":"93 496 10 32","__v":0}
{"_id":{"$oid":"593ff50016ff378afdf59662"},"name":"Fundació Suñol - Nivell Z…","address":"Rosselló 240","telf":"934 961 032","__v":0}
{"_id":{"$oid":"593ff50016ff378afdf59663"},"name":"Fundación MAPFRE","address":"c/ Diputació, 250","telf":"934 012 603","__v":0}
{"_id":{"$oid":"593ff50016ff378afdf59664"},"name":"Galeria 3 Punts","address":"Enric Granados 21","telf":"934 512 348","__v":0}
{"_id":{"$oid":"593ff50016ff378afdf59665"},"name":"Galeria Àmbit","address":"Consell de Cent, 282","telf":"934 881 800","__v":0}
{"_id":{"$oid":"593ff50016ff378afdf59666"},"name":"Galeria Artevistas","address":"Ptge. del Crèdit 4","telf":"935 130 465","__v":0}
{"_id":{"$oid":"593ff50016ff378afdf59667"},"name":"Galeria Carles Taché","address":"Mèxic, 19 - Passatge interior","telf":"934 878 836","__v":0}
{"_id":{"$oid":"593ff50016ff378afdf59668"},"name":"Galeria Esther Montoriol","address":"Diputació 339","telf":"932 448 521","__v":0}
{"_id":{"$oid":"593ff50016ff378afdf59669"},"name":"Galeria Joan Gaspar","address":"Pl. Letamendi 1","telf":"933 230 748","__v":0}
{"_id":{"$oid":"593ff50016ff378afdf5966a"},"name":"Galeria Joan Prats","address":"Balmes, 54","telf":"932 160 290","__v":0}
{"_id":{"$oid":"593ff50016ff378afdf5966b"},"name":"Galeria Jordi Barnadas","address":"Consell de Cent 347","telf":"932 156 365","__v":0}
{"_id":{"$oid":"593ff50016ff378afdf5966c"},"name":"Galeria L\u0026B","address":"Àlaba, 58","telf":"","__v":0}
{"_id":{"$oid":"593ff50016ff378afdf5966d"},"name":"Galeria Marc Domènech","address":"Ptge Mercader 12","telf":"935 951 482","__v":0}
{"_id":{"$oid":"593ff50016ff378afdf5966e"},"name":"Galeria Mayoral","address":"Consell de Cent 286","telf":"934 880 283","__v":0}
{"_id":{"$oid":"593ff50016ff378afdf5966f"},"name":"Galeria Miguel Marcos","address":"Jonqueres 10","telf":"933 192 627","__v":0}
{"_id":{"$oid":"593ff50016ff378afdf59670"},"name":"Galeria Miquel Alzueta","address":"Sèneca 9-11, int. baixos","telf":"932 389 750","__v":0}
{"_id":{"$oid":"593ff50016ff378afdf59671"},"name":"Galeria N2","address":"Enric Granados 61","telf":"934 520 592","__v":0}
{"_id":{"$oid":"593ff50016ff378afdf59672"},"name":"Galería RocioSantaCruz","address":"Gran Via de Les Corts Catalanes, 627","telf":"936 33 83 60","__v":0}
{"_id":{"$oid":"593ff50016ff378afdf59673"},"name":"Galeria Senda","address":"c/ Trafalgar, 32","telf":"934 882 199","__v":0}
{"_id":{"$oid":"593ff50016ff378afdf59674"},"name":"Galeria Trama","address":"Petritxol 5","telf":"933 174 877","__v":0}
{"_id":{"$oid":"593ff50016ff378afdf59675"},"name":"Galería Víctor Lope Arte …","address":"Aribau, 75","telf":"","__v":0}
{"_id":{"$oid":"593ff50016ff378afdf59676"},"name":"Gràcia Territori Sonor","address":"Igualada 10","telf":"","__v":0}
{"_id":{"$oid":"593ff50016ff378afdf59678"},"name":"Hans \u0026 Fr…","address":"c/ Sant Gil, 17","telf":"934 637 545","__v":0}
{"_id":{"$oid":"593ff50016ff378afdf59677"},"name":"H2O","address":"Verdi 152","telf":"934 151 801","__v":0}
{"_id":{"$oid":"593ff50016ff378afdf59679"},"name":"Homesession","address":"Creu dels Molers, 15","telf":"","__v":0}
{"_id":{"$oid":"593ff50016ff378afdf5967a"},"name":"I.E. Fotogràfics","address":"Comte d'Urgell 187. Recinte Escola Industrial","telf":"","__v":0}
{"_id":{"$oid":"593ff50016ff378afdf5967b"},"name":"Il Mondo","address":"Calàbria 178","telf":"931 882 323","__v":0}
{"_id":{"$oid":"593ff50016ff378afdf5967c"},"name":"La Capella","address":"Hospital 56","telf":"934 427 171","__v":0}
{"_id":{"$oid":"593ff50016ff378afdf5967d"},"name":"La Pedrera","address":"Provença 261-265","telf":"902 20 21 38","__v":0}
{"_id":{"$oid":"593ff50016ff378afdf5967e"},"name":"La Virreina","address":"La Rambla 99","telf":"933 161 000","__v":0}
{"_id":{"$oid":"593ff50016ff378afdf5967f"},"name":"M d'Hist. Catalunya","address":"Pl. Pau Vila 3. Palau de Mar","telf":"932 254 700","__v":0}
{"_id":{"$oid":"593ff50016ff378afdf59680"},"name":"MACBA","address":"Pl. dels Àngels 1","telf":"934 120 810","__v":0}
{"_id":{"$oid":"593ff50016ff378afdf59681"},"name":"Marlborough Barcelona","address":"Enric Granados 68","telf":"934 674 454","__v":0}
{"_id":{"$oid":"593ff50016ff378afdf59682"},"name":"Miscelänea","address":"Guàrdia 10","telf":"933 179 398","__v":0}
{"_id":{"$oid":"593ff50016ff378afdf59683"},"name":"Mobile World Centre","address":"Fontanella, 2","telf":"","__v":0}
{"_id":{"$oid":"593ff50016ff378afdf59684"},"name":"MUHBA (Museu d'Història d…","address":"Pl. del Rei s/n","telf":"933 151 111","__v":0}
{"_id":{"$oid":"593ff50016ff378afdf59685"},"name":"Museu Blau","address":"Museu Blau, Parque del Fórum, Plaça Leonardo da Vi","telf":"932 566 002","__v":0}
{"_id":{"$oid":"593ff50016ff378afdf5968a"},"name":"Museu Etnològic","address":"Pg. Santa Madrona s/n","telf":"934 246 807","__v":0}
{"_id":{"$oid":"593ff50016ff378afdf59689"},"name":"Museu Egipci","address":"València 284","telf":"934 880 188","image":"http://www.happybarcelona.eu/images/museos/museu-egipci-10.jpg","openingTimes":"WINTER TIMES \n (7 January - 21 June and 12 September - 30 November) \n Monday to Friday, from 10h to 14h and from 16h to 20h. Saturday from 10h to 20h. Sunday from 10h to 14h. \n (CHRISTMAS 1 December - 5 January) \n Monday to Saturday from 10h to 20h. Sunday from 10h to 14h. Closed: 1 and 6 January, 25 and 26 December. \n SUMMER TIMES \n (22 June - 11 September) \n Monday to Saturday from 10h to 20h. Sunday from 10h to 14h. \n EASTER AND PUBLIC HOLIDAYS \n Monday to Saturday from 10h to 20h. Sunday from 10h to 14h.","__v":0}
{"_id":{"$oid":"593ff50016ff378afdf59686"},"name":"Museu d'Arqueologia","address":"Pg. Santa Madrona 39-41","telf":"934 246 577","__v":0}
{"_id":{"$oid":"593ff50016ff378afdf59687"},"name":"Museu del Disseny","address":"Pl. Glòries 37","telf":"933 091 540","__v":0}
{"_id":{"$oid":"593ff50016ff378afdf5968b"},"name":"Museu Frederic Marès","address":"Plaça de Sant Iu, 5","telf":"932 563 500","__v":0}
{"_id":{"$oid":"593ff50016ff378afdf5968c"},"name":"Museu Marítim","address":"Av. Drassanes 1","telf":"933 429 920","__v":0}
{"_id":{"$oid":"593ff50016ff378afdf59691"},"name":"Opera","address":"Mallorca, 193","telf":"","__v":0}
{"_id":{"$oid":"593ff50016ff378afdf59690"},"name":"NoguerasBlanchard","address":"c/ Isaac Peral, 7","telf":"934 636 313","__v":0}
{"_id":{"$oid":"593ff50016ff378afdf59695"},"name":"Reial Cercle Artístic","address":"Arcs 5","telf":"93 318 78 66","__v":0}
{"_id":{"$oid":"593ff50016ff378afdf59688"},"name":"Museu del Modernisme Cata…","address":"Balmes 48","telf":"932 722 896","__v":0}
{"_id":{"$oid":"593ff50016ff378afdf5968e"},"name":"Museu Picasso","address":"Montcada 15-23","telf":"932 563 000","__v":0}
{"_id":{"$oid":"593ff50016ff378afdf5968d"},"name":"Museu Nacional d'Art de C…","address":"Palau Nacional. Montjuïc","telf":"936 220 360","__v":0}
{"_id":{"$oid":"593ff50016ff378afdf59693"},"name":"Piramidón Centre d'Art Co…","address":"Concili de Trento 313, 16a","telf":"932 780 768","__v":0}
{"_id":{"$oid":"593ff50016ff378afdf59692"},"name":"Palau Robert","address":"Pg. de Gràcia 107","telf":"932 384 000","__v":0}
{"_id":{"$oid":"593ff50016ff378afdf5968f"},"name":"Mutuo Centro de Arte","address":"Méndez Núñez, 7","telf":"","__v":0}
{"_id":{"$oid":"593ff50016ff378afdf59696"},"name":"Sardinuka","address":"Plaça de Narcís Oller, 6 PB Local, 4","telf":"932 807 215","__v":0}
{"_id":{"$oid":"593ff50016ff378afdf59698"},"name":"Untitled BCN","address":"Topazi 14","telf":"932 188 854","__v":0}
{"_id":{"$oid":"593ff50016ff378afdf59694"},"name":"ProjecteSD","address":"Passatge Mercader 8, baixos","telf":"934 881 360","__v":0}
{"_id":{"$oid":"593ff50016ff378afdf59697"},"name":"Suara Store","address":"Fusina, 6","telf":"","__v":0}
{"_id":{"$oid":"593ff50016ff378afdf59699"},"name":"Werner Thöni Artspace","address":"Legalitat 49","telf":"","__v":0}
{"_id":{"$oid":"593ff50016ff378afdf5969a"},"name":"Zielinsky Art","address":"Passatge de Mercader, 10","telf":"93 268 45 75","__v":0}
